README.rst
setup.py
filespy/__init__.py
filespy.egg-info/PKG-INFO
filespy.egg-info/SOURCES.txt
filespy.egg-info/dependency_links.txt
filespy.egg-info/top_level.txt
filespy.egg-info/zip-safe