Metadata-Version: 1.1
Name: filespy
Version: 1.1
Summary: find changes in a directory
Home-page: https://github.com/localvoid/py-filespy/
Author: Boris Kaul
Author-email: me@boriskaul.com
License: UNKNOWN
Download-URL: https://github.com/localvoid/py-filespy/tarball/master
Platform: Any
Classifier: Development Status :: 5 - Production/Stable
Classifier: License :: OSI Approved :: BSD License
Classifier: Programming Language :: Python
Classifier: Programming Language :: Python :: 3
Classifier: Intended Audience :: Developers
